{
  "project_info": {
    "project_number": "46898577180",
    "firebase_url": "https://market-services-c1e01-default-rtdb.firebaseio.com",
    "project_id": "market-services-c1e01",
    "storage_bucket": "market-services-c1e01.firebasestorage.app"
  },
  "client": [
    {
      "client_info": {
        "mobilesdk_app_id": "1:46898577180:android:dfaab9915457fcfeb104d9",
        "android_client_info": {
          "package_name": "com.fixkar.app"
        }
      },
      "oauth_client": [],
      "api_key": [
        {
          "current_key": "AIzaSyDrzx7tUpHgCLhnTQYUOqo-HVjO_RaRoSM"
        }
      ],
      "services": {
        "appinvite_service": {
          "other_platform_oauth_client": []
        }
      }
    }
  ],
  "configuration_version": "1"
}